pybs/__init__.py
pybs/cli.py
pybs/server/__init__.py
pybs/server/sshconf.py
ppbs-0.1.0.dist-info/LICENSE
ppbs-0.1.0.dist-info/METADATA
ppbs-0.1.0.dist-info/WHEEL
ppbs-0.1.0.dist-info/top_level.txt
ppbs-0.1.0.dist-info/RECORD
